[{"content":"","date":"24 Feb, 2023","permalink":"/","section":"","summary":"","title":""},{"content":"","date":"24 Feb, 2023","permalink":"/posts/","section":"","summary":"","title":""},{"content":" hello there\u003e hello there # this is the first post that i am trialing for this hugo site.\nnext steps\u003e next steps # if all goes well, i might sync this git project to github and deploy it to cloudfare\nsome stuff to worry about\u003e some stuff to worry about # item one item two item 3 list one list two $$ \\mathcal{L} = -\\frac{1}{4} F_{\\mu \\nu} F^{\\mu \\nu} $$\nthis is a text with inline math, just testing the stuff guys, ensure it all works great \\( \\varphi = e^\\varepsilon \\psi \\).\nom-tat-sat\n","date":"24 Feb, 2023","permalink":"/posts/first-post/","section":"","summary":"hello there\u003e hello there # this is the first post that i am trialing for this hugo site.","title":"First Post"},{"content":"","date":"24 Feb, 2023","permalink":"/tags/tag1/","section":"Tags","summary":"","title":"tag1"},{"content":"","date":"24 Feb, 2023","permalink":"/tags/tag2/","section":"Tags","summary":"","title":"tag2"},{"content":"","date":"24 Feb, 2023","permalink":"/tags/","section":"Tags","summary":"","title":"Tags"},{"content":"","date":"1 Jan, 0001","permalink":"/about/","section":"","summary":"","title":""},{"content":"","date":"1 Jan, 0001","permalink":"/authors/","section":"Authors","summary":"","title":"Authors"},{"content":"","date":"1 Jan, 0001","permalink":"/categories/","section":"Categories","summary":"","title":"Categories"},{"content":"","date":"1 Jan, 0001","permalink":"/series/","section":"Series","summary":"","title":"Series"}]